{
  "id": "aed1c758-ace0-442d-ba18-cc89aa98a3a0",
  "prevId": "00000000-0000-0000-0000-000000000000",
  "version": "7",
  "dialect": "postgresql",
  "tables": {
    "public.chunks": {
      "name": "chunks",
      "schema": "",
      "columns": {
        "id": {
          "name": "id",
          "type": "uuid",
          "primaryKey": true,
          "notNull": true,
          "default": "gen_random_uuid()"
        },
        "repo_id": {
          "name": "repo_id",
          "type": "uuid",
          "primaryKey": false,
          "notNull": true
        },
        "file_path": {
          "name": "file_path",
          "type": "text",
          "primaryKey": false,
          "notNull": true
        },
        "start_line": {
          "name": "start_line",
          "type": "integer",
          "primaryKey": false,
          "notNull": true
        },
        "end_line": {
          "name": "end_line",
          "type": "integer",
          "primaryKey": false,
          "notNull": true
        },
        "text": {
          "name": "text",
          "type": "text",
          "primaryKey": false,
          "notNull": true
        }
      },
      "indexes": {},
      "foreignKeys": {
        "chunks_repo_id_repos_id_fk": {
          "name": "chunks_repo_id_repos_id_fk",
          "tableFrom": "chunks",
          "tableTo": "repos",
          "columnsFrom": [
            "repo_id"
          ],
          "columnsTo": [
            "id"
          ],
          "onDelete": "cascade",
          "onUpdate": "no action"
        }
      },
      "compositePrimaryKeys": {},
      "uniqueConstraints": {},
      "policies": {},
      "checkConstraints": {},
      "isRLSEnabled": false
    },
    "public.embeddings": {
      "name": "embeddings",
      "schema": "",
      "columns": {
        "id": {
          "name": "id",
          "type": "uuid",
          "primaryKey": true,
          "notNull": true,
          "default": "gen_random_uuid()"
        },
        "chunk_id": {
          "name": "chunk_id",
          "type": "uuid",
          "primaryKey": false,
          "notNull": true
        },
        "embedding": {
          "name": "embedding",
          "type": "vector(1536)",
          "primaryKey": false,
          "notNull": false
        }
      },
      "indexes": {},
      "foreignKeys": {
        "embeddings_chunk_id_chunks_id_fk": {
          "name": "embeddings_chunk_id_chunks_id_fk",
          "tableFrom": "embeddings",
          "tableTo": "chunks",
          "columnsFrom": [
            "chunk_id"
          ],
          "columnsTo": [
            "id"
          ],
          "onDelete": "cascade",
          "onUpdate": "no action"
        }
      },
      "compositePrimaryKeys": {},
      "uniqueConstraints": {
        "embeddings_chunk_id_unique": {
          "name": "embeddings_chunk_id_unique",
          "nullsNotDistinct": false,
          "columns": [
            "chunk_id"
          ]
        }
      },
      "policies": {},
      "checkConstraints": {},
      "isRLSEnabled": false
    },
    "public.feedback": {
      "name": "feedback",
      "schema": "",
      "columns": {
        "id": {
          "name": "id",
          "type": "uuid",
          "primaryKey": true,
          "notNull": true,
          "default": "gen_random_uuid()"
        },
        "repo_url": {
          "name": "repo_url",
          "type": "text",
          "primaryKey": false,
          "notNull": true
        },
        "message_id": {
          "name": "message_id",
          "type": "text",
          "primaryKey": false,
          "notNull": true
        },
        "value": {
          "name": "value",
          "type": "integer",
          "primaryKey": false,
          "notNull": true
        },
        "created_at": {
          "name": "created_at",
          "type": "timestamp",
          "primaryKey": false,
          "notNull": true,
          "default": "now()"
        }
      },
      "indexes": {},
      "foreignKeys": {},
      "compositePrimaryKeys": {},
      "uniqueConstraints": {},
      "policies": {},
      "checkConstraints": {},
      "isRLSEnabled": false
    },
    "public.repos": {
      "name": "repos",
      "schema": "",
      "columns": {
        "id": {
          "name": "id",
          "type": "uuid",
          "primaryKey": true,
          "notNull": true,
          "default": "gen_random_uuid()"
        },
        "url": {
          "name": "url",
          "type": "text",
          "primaryKey": false,
          "notNull": true
        },
        "branch": {
          "name": "branch",
          "type": "text",
          "primaryKey": false,
          "notNull": true
        },
        "indexed_at": {
          "name": "indexed_at",
          "type": "timestamp",
          "primaryKey": false,
          "notNull": false
        }
      },
      "indexes": {},
      "foreignKeys": {},
      "compositePrimaryKeys": {},
      "uniqueConstraints": {
        "repos_url_unique": {
          "name": "repos_url_unique",
          "nullsNotDistinct": false,
          "columns": [
            "url"
          ]
        }
      },
      "policies": {},
      "checkConstraints": {},
      "isRLSEnabled": false
    }
  },
  "enums": {},
  "schemas": {},
  "sequences": {},
  "roles": {},
  "policies": {},
  "views": {},
  "_meta": {
    "columns": {},
    "schemas": {},
    "tables": {}
  }
}